chop/__init__.py
chop/adversary.py
chop/constraints.py
chop/optim.py
chop/penalties.py
chop/stochastic.py
chop/utils/__init__.py
chop/utils/data.py
chop/utils/image.py
chop/utils/logging.py
chop/utils/utils.py
tests/__init__.py
tests/test_adversary.py
tests/test_constraints.py
tests/test_optim.py
tests/test_penalties.py
tests/test_stochastic.py
tests/test_utils.py
chop_pytorch-0.0.3.1.dist-info/LICENSE
chop_pytorch-0.0.3.1.dist-info/METADATA
chop_pytorch-0.0.3.1.dist-info/WHEEL
chop_pytorch-0.0.3.1.dist-info/top_level.txt
chop_pytorch-0.0.3.1.dist-info/RECORD
