Metadata-Version: 2.1
Name: chop-pytorch
Version: 0.0.3.1
Summary: Continuous and constrained optimization with PyTorch
Home-page: http://pypi.python.org/pypi/chop-pytorch
Author: Geoffrey Negiar
Author-email: geoffrey_negiar@berkeley.edu
License: UNKNOWN
Platform: UNKNOWN
Classifier: Development Status :: 3 - Alpha
Classifier: Intended Audience :: Science/Research
Classifier: Intended Audience :: Developers
Classifier: License :: OSI Approved :: BSD License
Classifier: Programming Language :: Python
Classifier: Programming Language :: Python :: 3
Classifier: Topic :: Software Development
Classifier: Operating System :: POSIX
Classifier: Operating System :: Unix
Requires-Dist: numpy
Requires-Dist: scipy
Requires-Dist: torch
Requires-Dist: torchvision
Requires-Dist: easydict
Requires-Dist: matplotlib
Requires-Dist: tqdm
